{
  "dependencies": {
    "appInsights1": {
      "resourceId": "/subscriptions/[parameters('subscriptionId')]/resourceGroups/[parameters('resourceGroupName')]/providers/microsoft.insights/components/etymology-staging",
      "type": "appInsights.azure",
      "connectionId": "APPINSIGHTS_CONNECTIONSTRING",
      "secretStore": "AzureAppSettings"
    },
    "mssql1": {
      "resourceId": "/subscriptions/[parameters('subscriptionId')]/resourceGroups/[parameters('resourceGroupName')]/providers/Microsoft.Sql/servers/etymology/databases/etymology-staging",
      "type": "mssql.azure",
      "connectionId": "Etymology",
      "secretStore": "AzureAppSettings"
    }
  }
}